realtimeaggregator/__init__.py
realtimeaggregator/__main__.py
realtimeaggregator/remote_settings.py
realtimeaggregator/logs/__init__.py
realtimeaggregator/logs/__main__.py
realtimeaggregator/logs/log_templates_pb2.py
realtimeaggregator/tasks/__init__.py
realtimeaggregator/tasks/archive.py
realtimeaggregator/tasks/compress.py
realtimeaggregator/tasks/download.py
realtimeaggregator/tasks/exceptions.py
realtimeaggregator/tasks/files.py
realtimeaggregator/tasks/filter.py
realtimeaggregator/tasks/task.py
realtimeaggregator-0.2.0.dist-info/DESCRIPTION.rst
realtimeaggregator-0.2.0.dist-info/METADATA
realtimeaggregator-0.2.0.dist-info/RECORD
realtimeaggregator-0.2.0.dist-info/WHEEL
realtimeaggregator-0.2.0.dist-info/entry_points.txt
realtimeaggregator-0.2.0.dist-info/metadata.json
realtimeaggregator-0.2.0.dist-info/top_level.txt
