Metadata-Version: 2.0
Name: realtimeaggregator
Version: 0.2.0
Summary: Software for aggregating realtime feeds
Home-page: https://github.com/jamespfennell/realtime-aggregator
Author: James Fennell
Author-email: jamespfennell@gmail.com
License: UNKNOWN
Download-URL: https://github.com/jamespfennell/realtime-aggregator/archive/0.2.0.tar.gz
Platform: UNKNOWN
Requires-Python: >=3.5
Requires-Dist: requests
Requires-Dist: gtfs-realtime-bindings
Requires-Dist: boto3
